[{"acronym":"LIK","practice_sessions":["recEFS2P3kqHpNeBM","recJenmrEhnNUvymS","rec7Y5ctPv9AOeMFc","recYAgwtNzzK1vrnv","recdgppwuw2W68G5u","recyGfjH5EIWshQ3F","recOk3YoIBZEJDlKl","recZpaIIj5dLerSG9","recTvDUVTxnwehdv2","rec2fzRYxHpHGdWs8","recxlB2XvyZ9dEDmX","recjY0B8QNshxn7Xr","recZQGje95bUvTXZb","recKnCIXnX0AQQEiz","reczyfAxlf2FZIynT","rec1aQwjoSMioVxMk","recjkRPbao8ozFQuZ","recqtEKXm0JCyzezs","rectMPPxJ29XMk2nL","recaEAWngRASbOkBG","reciCqYj0aXsr5ngO","recWCO49HSEEn66mc","recTgUqVNQ8eGVRXv","recNm5Wwj1W534Vxg","recpUcqNvgsDA3lNM","recoQwAnbNnt2KU7d","recS7zjuYwioA1TFh","rec6KStdQxKI22fGm","recFkXrbMN4rqeRIM","recXTG5QfRvfLtd40","recjUB1lCzmYqc2Zk","recrPArdm9HmoNhPP","recPKYPi5EpevsVWu","recazDzZtMj7d3xGA","recJyUNSFA51iNIwg","recZfHrSVgecO5vY9","rec8nyQPeRSzdi08Q","recf0s3A7dQXneyIg","rec4RKCiEWTfl4Tb7","recIgYv00CbNx9Dme","recaXJH8tt2L5Jj3e","recJKdsjXe8RtIUzR","rece7O54cWeQfytGJ","recvlyZrKrbV6Wani","recAi4UVStGC8kQda","recgTTFWC0SEEq4z6","recqQG5F1dA9vNdhd","recvoxBvZsp3HLjlM","recmNRAaBuMcFfw5W"],"name":"Linear Isomorphic Keyboard","id":"recAOa5OnDyNjvPUp"},{"acronym":"Individual","id":"recKum4LKvbaoFsd3"},{"acronym":"TK","practice_sessions":["rectybGmBSFf6W22v","recJ1O3RMjjEHmWNS","recpN4C6JeNXcQOMt","recysZZtCh3eS7UPr","rec9bjhlqp7IIUtOU","recYJFab208HOfRc2","recIPHs7nu4MWdGUO","recIyMdMdWKVHEyPG","recpSUeIPNOjOjgaI","rec2wSWE4pMtHtvXW","recFdVgGw1bcbRX38","rechXwjwZQ0tGWh2f","recU52mLmAraytkKT","recazJxIOm4ZxKjv6","rec5lXWDNiE0g2Xc4","rec9wzlQZ52JcoGrM","recsuEzRnKLFWGBhQ","reco9gZuK86rj3vH8","recQYUjQpLSdoGQHa","recedqJ3RyJiQCskS","rec3mQS0bJtFGIq0a","rectmoX9LX2wfLS3F","recDOiJykvw7j6FBM","recRPGoQR6DXDGcdx","recwheIExRzCUWU7Z","recB1UaTM1x284Jj4","recwYlAqZOm9zus7f","recueJoyXQTwPAXn8","recQ2BGsJpQAo2itY","recro0y8jZ1EWMKI5","rec2Zo8uDcazKubXh","rechy9AiiKYSIQAnH","recF5s7uG5jU6ThE3","recpVIREiHwxhudjm","recsqkmfZmQZeTJeX","reclX7xSczFUG3bil","rec8pr53q4zExBeBQ","recTeFQAGB4VoEXkj","receSvfZU3256rf8p","recSpofpDPEo3zqGN","rec0aT8h3xdwnC6Hq","recZtsmf5NP2MSkXU","rec9HN3uBAZBlUCEK","rec4AWrKgcE2zrccW","recHkh2IkeauGKnNT","rec0IHiodSTBJzZ9s","recjUmYXltLvjOETe","recNBuWkr12xbnd6n"],"name":"Traditional Keyboard","id":"recUlyK9YJLOblfTI"}]